authentication/__init__.py
authentication/impl/__init__.py
authentication/impl/auth_utility.py
authentication/impl/token_utility.py
authentication/middleware/__init__.py
authentication/middleware/auth_decorators.py
authentication/middleware/auth_extractor.py
authentication/models.py
authentication/routes/__init__.py
authentication/routes/account.py
authentication/routes/csrf.py
authentication/routes/login.py
authentication/routes/totp.py
authentication/schemes/__init__.py
authentication/schemes/auth.py
authentication/schemes/responses.py
authentication/schemes/totp.py
authentication/settings.py
authentication/utils/__init__.py
authentication/utils/common.py
authentication/utils/functions.py
authentication/utils/json.py
connectkit_fastapi_authentication-2.3.0.dist-info/METADATA
connectkit_fastapi_authentication-2.3.0.dist-info/WHEEL
connectkit_fastapi_authentication-2.3.0.dist-info/entry_points.txt
connectkit_fastapi_authentication-2.3.0.dist-info/licenses/LICENSE
connectkit_fastapi_authentication-2.3.0.dist-info/RECORD
