Metadata-Version: 2.1
Name: ConnectKit-FastAPI-Authentication
Version: 2.3.0
Summary: User accounts and jwt authentication for FastAPI services
Keywords: connectkit,authentication,authorization,jwt,totp,otp,fastapi
Author-Email: RealMetamorph <andr.timchuk@yandex.ru>
License: The MIT License (MIT)
Classifier: Development Status :: 4 - Beta
Classifier: Programming Language :: Python :: 3
Classifier: Intended Audience :: Developers
Classifier: Framework :: FastAPI
Classifier: License :: OSI Approved :: MIT License
Project-URL: Homepage, https://github.com/mtuciru/ConnectKit-FastAPI-Authentication/tree/wo_oauth
Project-URL: Repository, https://github.com/mtuciru/ConnectKit-FastAPI-Authentication.git
Requires-Python: >=3.10
Requires-Dist: ConnectKit-Database>=2.1.1
Requires-Dist: pydantic>=2.10.6
Requires-Dist: pydantic-settings>=2.8.1
Requires-Dist: fastapi>=0.115.11
Requires-Dist: PyJWT[crypto]>=2.10.1
Requires-Dist: argon2-cffi>=23.1.0
Requires-Dist: ietfparse>=1.9.0
Requires-Dist: filelock>=3.18.0
Requires-Dist: pyotp>=2.9.0
Requires-Dist: aiohttp>=3.12.12
Provides-Extra: orjson
Requires-Dist: orjson>=3.10.15; extra == "orjson"
Requires-Dist: ConnectKit-Database[orjson]>=2.1.1; extra == "orjson"
Provides-Extra: email
Requires-Dist: email_validator; extra == "email"
Provides-Extra: phone
Requires-Dist: phonenumbers; extra == "phone"
